<?xml version="1.0" encoding="UTF-8"?>
<news><new id="1" lang="ru"><name>КРАСОТА В КЕРАМИКЕ&lt;/br&gt;НОВАЯ ПОВЕРХНОСТЬ ДЛЯ АРХИТЕКТУРЫ</name><text>Название Cotto D`este зарекомендовало себя, как одно из самых престижных имен в области керамики. Наши творения напоминают красоту, качество и престиж и являются результатом наших страстных и непрерывных исследований. Поиск красоты – это не миссия, а призвание, которое позволило нам достичь высокого уровня совершенства, что засвидетельствовано доверием, оказанным нашим творениям архитекторами и дизайнерами интерьеров по всему миру.</text><img>http://ceramogrand.by/data/uploads/news/1.jpg</img><href/></new><new id="2" lang="ru"><name>THE LANGUAGE OF WOOD</name><text>Дерево говорит с нашим сердцем. Цвет волокна, ткстура и удовольствие от прикосновения - прямой и неподвластный времени язык. Древесина, отобранная Cotto D`este собранная в двух хорошо структурированных коллекциях рассказываетт о жизни и отношениях, чтобы придать форму теплу среды, которые элегантно просты, в балансе между традициями и современностью.</text><img>http://ceramogrand.by/data/uploads/news/2.jpg</img><href/></new></news>
