<?xml version="1.0" encoding="UTF-8"?>
<item><pubDate>Fri, 27 Dec 2019 11:53:11 +0300</pubDate><title><![CDATA[Внутри]]></title><url><![CDATA[vnutri]]></url><meta><![CDATA[]]></meta><metad><![CDATA[]]></metad><menu><![CDATA[Внутри]]></menu><menuStatus><![CDATA[Y]]></menuStatus><template><![CDATA[template.php]]></template><parent><![CDATA[ispolzovanie]]></parent><content><![CDATA[]]></content><private><![CDATA[]]></private><author><![CDATA[admin]]></author><creDate>Thu, 26 Dec 2019 12:28:41 +0300</creDate><user><![CDATA[admin]]></user><menuOrder><![CDATA[1]]></menuOrder></item>
